vaexede/__init__.py
vaexede/custom_activation.py
vaexede/load_models.py
vaexede/models.py
vaexede/preprocess.py
vaexede/trained_models/DlTT_EDE_ref.npy
vaexede/trained_models/DlTT_LCDM_ref.npy
vaexede/trained_models/best_model_5dim_1e-05beta_lcdmrefsuffix_30lmin_normlog.data-00000-of-00001
vaexede/trained_models/best_model_5dim_1e-05beta_lcdmrefsuffix_30lmin_normlog.index
vaexede/trained_models/best_model_8dim_2e-05beta_ederefsuffix_30lmin_normlog.data-00000-of-00001
vaexede/trained_models/best_model_8dim_2e-05beta_ederefsuffix_30lmin_normlog.index
vaexede/trained_models/log10_ratio_mean_new_ede.npy
vaexede/trained_models/log10_ratio_mean_new_lcdm.npy
vaexede/trained_models/log10_ratio_std_new_ede.npy
vaexede/trained_models/log10_ratio_std_new_lcdm.npy
vaexede-0.1.0.dist-info/licenses/LICENSE.txt
vaexede-0.1.0.dist-info/licenses/LICENSE_EXT.txt
vaexede-0.1.0.dist-info/METADATA
vaexede-0.1.0.dist-info/WHEEL
vaexede-0.1.0.dist-info/top_level.txt
vaexede-0.1.0.dist-info/RECORD
