Metadata-Version: 2.4
Name: vaexede
Version: 0.1.0
Summary: Trained models for EDE and LCDM VAEs
Home-page: https://github.com/dpiras/VAExEDE
Author: Davide Piras
Author-email: dr.davide.piras@gmail.com
License: GNU General Public License v3.0 (GPLv3)
Classifier: Programming Language :: Python :: 3
Classifier: License :: OSI Approved :: GNU General Public License v3 (GPLv3)
Classifier: Operating System :: OS Independent
Requires-Python: >=3.10
License-File: LICENSE.txt
License-File: LICENSE_EXT.txt
Requires-Dist: tensorflow
Requires-Dist: keras<3
Requires-Dist: matplotlib
Requires-Dist: numpy
Dynamic: author
Dynamic: author-email
Dynamic: classifier
Dynamic: description
Dynamic: description-content-type
Dynamic: home-page
Dynamic: license
Dynamic: license-file
Dynamic: requires-dist
Dynamic: requires-python
Dynamic: summary
